ai_gateway/__init__.py
ai_gateway/abilities.py
ai_gateway/agent.py
ai_gateway/callbacks.py
ai_gateway/canonicalizer.py
ai_gateway/config.py
ai_gateway/llm.py
ai_gateway/prompts_router.py
ai_gateway/registry.py
ai_gateway/schemas.py
stum_ai_gateway-0.1.11.dist-info/METADATA
stum_ai_gateway-0.1.11.dist-info/WHEEL
stum_ai_gateway-0.1.11.dist-info/licenses/LICENSE
stum_ai_gateway-0.1.11.dist-info/RECORD
