Metadata-Version: 2.4
Name: stum-ai-gateway
Version: 0.1.11
Summary: NatBus-to-LLM agent gateway (contract-validated, iterative planning)
Project-URL: Homepage, https://servicepod.net
Project-URL: Source, https://servicepod.net
Project-URL: Issues, https://servicepod.net
Author-email: Servicepod <admin@servicepod.net>
License: MIT License
License-File: LICENSE
Keywords: agent,gateway,jetstream,llm,nats
Requires-Python: >=3.11
Requires-Dist: jsonschema>=4.23
Requires-Dist: natbus>=0.1.17
Requires-Dist: nats-py>=2.11.0
Provides-Extra: dev
Requires-Dist: pytest-asyncio>=1.1.0; extra == 'dev'
Requires-Dist: pytest>=8.4.1; extra == 'dev'
